{"lastUpdated":1650022503425,"username":"RosyUnicornSans","scores":[{"xp":3638,"rank":455,"cardId":303},{"xp":13862,"rank":370,"cardId":114},{"xp":28321,"rank":315,"cardId":289},{"xp":7802,"rank":497,"cardId":532},{"xp":28493,"rank":107,"cardId":151},{"xp":22927,"rank":259,"cardId":524},{"xp":6399,"rank":282,"cardId":606},{"xp":28409,"rank":204,"cardId":48},{"xp":19619,"rank":421,"cardId":165},{"xp":14430,"rank":64,"cardId":635},{"xp":53048,"rank":471,"cardId":110},{"xp":48558,"rank":495,"cardId":61}]}