{"lastUpdated":1650627328046,"username":"LukeeeIDK","scores":[{"xp":69177,"rank":107,"cardId":1},{"xp":71196,"rank":284,"cardId":401},{"xp":30888,"rank":330,"cardId":32},{"xp":22235,"rank":282,"cardId":601},{"xp":15020,"rank":191,"cardId":220},{"xp":6550,"rank":399,"cardId":285},{"xp":24485,"rank":263,"cardId":600},{"xp":5368,"rank":344,"cardId":384},{"xp":12683,"rank":179,"cardId":385},{"xp":6071,"rank":281,"cardId":680},{"xp":5001,"rank":186,"cardId":679},{"xp":5257,"rank":463,"cardId":407},{"xp":80868,"rank":46,"cardId":450},{"xp":44598,"rank":496,"cardId":246},{"xp":7690,"rank":457,"cardId":603},{"xp":56544,"rank":67,"cardId":174},{"xp":20732,"rank":339,"cardId":599},{"xp":324,"rank":406,"cardId":666},{"xp":3711,"rank":375,"cardId":629},{"xp":36659,"rank":173,"cardId":15},{"xp":21240,"rank":436,"cardId":243},{"xp":8650,"rank":455,"cardId":532},{"xp":17844,"rank":484,"cardId":104},{"xp":5106,"rank":212,"cardId":683},{"xp":21026,"rank":140,"cardId":126},{"xp":4461,"rank":316,"cardId":681},{"xp":4901,"rank":242,"cardId":684},{"xp":88502,"rank":92,"cardId":58},{"xp":4236,"rank":164,"cardId":686},{"xp":53061,"rank":345,"cardId":273},{"xp":3677,"rank":216,"cardId":685},{"xp":22966,"rank":335,"cardId":36},{"xp":29446,"rank":285,"cardId":616},{"xp":57502,"rank":104,"cardId":17},{"xp":4406,"rank":241,"cardId":687}]}