{"lastUpdated":1647722134616,"username":"Moonwolfpack","scores":[{"xp":38114,"rank":373,"cardId":164},{"xp":128290,"rank":65,"cardId":378},{"xp":24395,"rank":326,"cardId":136},{"xp":46547,"rank":9,"cardId":149},{"xp":36766,"rank":233,"cardId":217},{"xp":40843,"rank":388,"cardId":58},{"xp":16433,"rank":370,"cardId":142},{"xp":57320,"rank":35,"cardId":195},{"xp":18145,"rank":282,"cardId":143},{"xp":10136,"rank":340,"cardId":414},{"xp":36289,"rank":18,"cardId":228},{"xp":32790,"rank":257,"cardId":521},{"xp":115213,"rank":14,"cardId":127},{"xp":108677,"rank":33,"cardId":424},{"xp":18340,"rank":435,"cardId":48},{"xp":52907,"rank":444,"cardId":227},{"xp":80245,"rank":226,"cardId":110},{"xp":15143,"rank":404,"cardId":573},{"xp":91111,"rank":125,"cardId":28}]}