{"lastUpdated":1646901595528,"username":"godmano","scores":[{"xp":11219,"rank":263,"cardId":567},{"xp":25582,"rank":344,"cardId":196},{"xp":70569,"rank":91,"cardId":1},{"xp":24102,"rank":415,"cardId":433},{"xp":16215,"rank":201,"cardId":520},{"xp":28732,"rank":323,"cardId":2},{"xp":15348,"rank":392,"cardId":160},{"xp":66440,"rank":7,"cardId":499},{"xp":15095,"rank":465,"cardId":40},{"xp":9621,"rank":420,"cardId":187},{"xp":19637,"rank":167,"cardId":494},{"xp":18190,"rank":277,"cardId":238},{"xp":32096,"rank":135,"cardId":252},{"xp":114288,"rank":58,"cardId":58},{"xp":5314,"rank":411,"cardId":438},{"xp":21056,"rank":39,"cardId":193},{"xp":80895,"rank":29,"cardId":396},{"xp":40748,"rank":160,"cardId":503},{"xp":18758,"rank":202,"cardId":541},{"xp":51837,"rank":113,"cardId":11},{"xp":18225,"rank":190,"cardId":406},{"xp":37364,"rank":432,"cardId":504},{"xp":15362,"rank":118,"cardId":248},{"xp":17687,"rank":222,"cardId":151},{"xp":17225,"rank":405,"cardId":124},{"xp":55371,"rank":67,"cardId":104},{"xp":35438,"rank":414,"cardId":14},{"xp":38055,"rank":36,"cardId":386},{"xp":24866,"rank":408,"cardId":34},{"xp":22513,"rank":298,"cardId":198},{"xp":16457,"rank":233,"cardId":411},{"xp":6016,"rank":257,"cardId":153},{"xp":25062,"rank":237,"cardId":24},{"xp":21861,"rank":185,"cardId":293},{"xp":28800,"rank":242,"cardId":49},{"xp":23566,"rank":325,"cardId":127},{"xp":36871,"rank":389,"cardId":262},{"xp":33224,"rank":54,"cardId":526},{"xp":15362,"rank":187,"cardId":426},{"xp":33396,"rank":282,"cardId":408},{"xp":15795,"rank":70,"cardId":292},{"xp":25196,"rank":232,"cardId":240},{"xp":21553,"rank":452,"cardId":424},{"xp":27488,"rank":337,"cardId":318},{"xp":27515,"rank":252,"cardId":236},{"xp":9599,"rank":417,"cardId":423},{"xp":28405,"rank":202,"cardId":165},{"xp":64563,"rank":136,"cardId":264},{"xp":73567,"rank":274,"cardId":227},{"xp":146627,"rank":58,"cardId":273},{"xp":32790,"rank":80,"cardId":154},{"xp":36844,"rank":470,"cardId":39},{"xp":56177,"rank":112,"cardId":123},{"xp":86775,"rank":58,"cardId":117},{"xp":139958,"rank":136,"cardId":214},{"xp":20934,"rank":296,"cardId":573},{"xp":16819,"rank":369,"cardId":267},{"xp":110098,"rank":400,"cardId":444},{"xp":25959,"rank":308,"cardId":564}]}