{"lastUpdated":1650238660018,"username":"dukeripper","scores":[{"xp":11098,"rank":314,"cardId":222},{"xp":12117,"rank":410,"cardId":550},{"xp":10362,"rank":404,"cardId":515},{"xp":8059,"rank":136,"cardId":417},{"xp":13382,"rank":288,"cardId":275},{"xp":5809,"rank":273,"cardId":498},{"xp":17742,"rank":383,"cardId":434},{"xp":6714,"rank":187,"cardId":519},{"xp":62232,"rank":371,"cardId":147},{"xp":9485,"rank":297,"cardId":313},{"xp":23914,"rank":203,"cardId":468},{"xp":12795,"rank":404,"cardId":116},{"xp":10470,"rank":362,"cardId":274},{"xp":9081,"rank":301,"cardId":673},{"xp":3033,"rank":468,"cardId":465},{"xp":10923,"rank":293,"cardId":528},{"xp":7891,"rank":423,"cardId":671},{"xp":32657,"rank":370,"cardId":466},{"xp":742,"rank":479,"cardId":649},{"xp":9040,"rank":429,"cardId":293},{"xp":7711,"rank":363,"cardId":674},{"xp":20427,"rank":385,"cardId":530},{"xp":36390,"rank":437,"cardId":287},{"xp":34705,"rank":419,"cardId":35},{"xp":7240,"rank":430,"cardId":502},{"xp":55072,"rank":293,"cardId":21},{"xp":5172,"rank":183,"cardId":590},{"xp":6064,"rank":274,"cardId":529},{"xp":5176,"rank":331,"cardId":581},{"xp":28347,"rank":248,"cardId":267}]}