{"lastUpdated":1655139485570,"username":"rererere5213325","scores":[{"xp":42157,"rank":358,"cardId":1},{"xp":2576,"rank":287,"cardId":619},{"xp":8407,"rank":470,"cardId":220},{"xp":12291,"rank":366,"cardId":515},{"xp":33479,"rank":103,"cardId":27},{"xp":11506,"rank":155,"cardId":612},{"xp":29098,"rank":305,"cardId":509},{"xp":26043,"rank":60,"cardId":589},{"xp":20800,"rank":192,"cardId":393},{"xp":6234,"rank":266,"cardId":292},{"xp":18042,"rank":134,"cardId":410},{"xp":18918,"rank":277,"cardId":566},{"xp":24508,"rank":448,"cardId":616},{"xp":41131,"rank":245,"cardId":17}]}