{"lastUpdated":1649000357196,"username":"Gamaxl","scores":[{"xp":2534,"rank":300,"cardId":587},{"xp":19952,"rank":247,"cardId":311},{"xp":5057,"rank":472,"cardId":496},{"xp":8817,"rank":386,"cardId":499},{"xp":8574,"rank":317,"cardId":166},{"xp":13443,"rank":390,"cardId":56},{"xp":9724,"rank":192,"cardId":407},{"xp":9449,"rank":189,"cardId":245},{"xp":5056,"rank":323,"cardId":594},{"xp":5092,"rank":330,"cardId":276},{"xp":31303,"rank":494,"cardId":262},{"xp":13303,"rank":116,"cardId":229},{"xp":17818,"rank":355,"cardId":240}]}