{"lastUpdated":1655580886340,"username":"Laren","scores":[{"xp":20349,"rank":390,"cardId":434},{"xp":16901,"rank":265,"cardId":275},{"xp":18484,"rank":154,"cardId":480},{"xp":20081,"rank":315,"cardId":142},{"xp":15809,"rank":187,"cardId":313},{"xp":4211,"rank":424,"cardId":588},{"xp":7121,"rank":254,"cardId":594},{"xp":18789,"rank":240,"cardId":394},{"xp":695,"rank":279,"cardId":644},{"xp":8677,"rank":487,"cardId":418},{"xp":21977,"rank":76,"cardId":727},{"xp":31854,"rank":351,"cardId":106},{"xp":5927,"rank":271,"cardId":647}]}