{"lastUpdated":1654512141032,"username":"Mimer","scores":[{"xp":6670,"rank":322,"cardId":492},{"xp":8572,"rank":256,"cardId":226},{"xp":25833,"rank":212,"cardId":312},{"xp":6294,"rank":283,"cardId":384},{"xp":16743,"rank":490,"cardId":434},{"xp":2560,"rank":488,"cardId":561},{"xp":13650,"rank":216,"cardId":480},{"xp":6514,"rank":299,"cardId":245},{"xp":9986,"rank":241,"cardId":740},{"xp":2557,"rank":295,"cardId":646},{"xp":10302,"rank":322,"cardId":313},{"xp":3338,"rank":484,"cardId":629},{"xp":1346,"rank":419,"cardId":628},{"xp":15355,"rank":286,"cardId":394},{"xp":9482,"rank":128,"cardId":707},{"xp":14845,"rank":188,"cardId":410},{"xp":7323,"rank":225,"cardId":727},{"xp":5694,"rank":366,"cardId":581}]}