{"lastUpdated":1655753713186,"username":"spadesofhearts5","scores":[{"xp":7731,"rank":268,"cardId":492},{"xp":6300,"rank":377,"cardId":490},{"xp":9746,"rank":421,"cardId":224},{"xp":9897,"rank":281,"cardId":610},{"xp":45877,"rank":49,"cardId":311},{"xp":30686,"rank":119,"cardId":300},{"xp":36534,"rank":292,"cardId":309},{"xp":13442,"rank":222,"cardId":251},{"xp":8316,"rank":447,"cardId":499},{"xp":20338,"rank":364,"cardId":600},{"xp":41845,"rank":94,"cardId":40},{"xp":24565,"rank":245,"cardId":29},{"xp":15889,"rank":470,"cardId":495},{"xp":8079,"rank":230,"cardId":611},{"xp":60749,"rank":43,"cardId":314},{"xp":14457,"rank":152,"cardId":237},{"xp":22569,"rank":249,"cardId":281},{"xp":7099,"rank":218,"cardId":498},{"xp":15365,"rank":116,"cardId":467},{"xp":60280,"rank":77,"cardId":6},{"xp":69944,"rank":254,"cardId":107},{"xp":9717,"rank":198,"cardId":407},{"xp":53955,"rank":129,"cardId":450},{"xp":11747,"rank":477,"cardId":247},{"xp":10218,"rank":173,"cardId":245},{"xp":9190,"rank":425,"cardId":125},{"xp":47965,"rank":497,"cardId":10},{"xp":22631,"rank":232,"cardId":143},{"xp":8770,"rank":421,"cardId":603},{"xp":6609,"rank":207,"cardId":593},{"xp":8847,"rank":315,"cardId":298},{"xp":11988,"rank":85,"cardId":588},{"xp":36057,"rank":302,"cardId":11},{"xp":31885,"rank":135,"cardId":301},{"xp":16309,"rank":99,"cardId":594},{"xp":10216,"rank":284,"cardId":397},{"xp":11232,"rank":440,"cardId":215},{"xp":66991,"rank":17,"cardId":296},{"xp":18813,"rank":372,"cardId":524},{"xp":27079,"rank":341,"cardId":509},{"xp":48046,"rank":210,"cardId":18},{"xp":7725,"rank":374,"cardId":589},{"xp":4036,"rank":271,"cardId":707},{"xp":8459,"rank":484,"cardId":282},{"xp":8115,"rank":223,"cardId":547},{"xp":6616,"rank":250,"cardId":591},{"xp":52347,"rank":360,"cardId":273},{"xp":45937,"rank":32,"cardId":526},{"xp":8508,"rank":345,"cardId":410},{"xp":24017,"rank":461,"cardId":549},{"xp":22100,"rank":125,"cardId":556},{"xp":20368,"rank":256,"cardId":249},{"xp":60542,"rank":414,"cardId":110},{"xp":4762,"rank":220,"cardId":590}]}