{"lastUpdated":1649047573073,"username":"rapper47","scores":[{"xp":22392,"rank":460,"cardId":7},{"xp":36834,"rank":397,"cardId":164},{"xp":23602,"rank":257,"cardId":601},{"xp":16777,"rank":456,"cardId":5},{"xp":44683,"rank":67,"cardId":252},{"xp":12030,"rank":366,"cardId":440},{"xp":9248,"rank":425,"cardId":500},{"xp":19494,"rank":187,"cardId":215},{"xp":34419,"rank":142,"cardId":524},{"xp":42186,"rank":265,"cardId":18},{"xp":26819,"rank":50,"cardId":589},{"xp":24457,"rank":441,"cardId":408},{"xp":17296,"rank":296,"cardId":531},{"xp":9549,"rank":318,"cardId":192},{"xp":3573,"rank":358,"cardId":716},{"xp":65404,"rank":449,"cardId":214},{"xp":1485,"rank":474,"cardId":647}]}