{"lastUpdated":1651419674256,"username":"dimon12345rus","scores":[{"xp":24801,"rank":421,"cardId":433},{"xp":8188,"rank":448,"cardId":567},{"xp":61965,"rank":132,"cardId":1},{"xp":44071,"rank":294,"cardId":164},{"xp":58075,"rank":29,"cardId":285},{"xp":63267,"rank":137,"cardId":402},{"xp":974,"rank":490,"cardId":621},{"xp":50786,"rank":436,"cardId":246},{"xp":62780,"rank":96,"cardId":16},{"xp":65597,"rank":48,"cardId":140},{"xp":54622,"rank":99,"cardId":239},{"xp":51484,"rank":327,"cardId":139},{"xp":40444,"rank":331,"cardId":14},{"xp":3359,"rank":347,"cardId":626},{"xp":56476,"rank":25,"cardId":194},{"xp":30016,"rank":397,"cardId":466},{"xp":28963,"rank":343,"cardId":109},{"xp":53340,"rank":48,"cardId":150},{"xp":36291,"rank":146,"cardId":165},{"xp":17700,"rank":491,"cardId":505},{"xp":55741,"rank":412,"cardId":8}]}