{"lastUpdated":1646890457746,"username":"SUPERBOMBARDINO","scores":[{"xp":41711,"rank":312,"cardId":1},{"xp":15438,"rank":85,"cardId":226},{"xp":36900,"rank":143,"cardId":136},{"xp":27091,"rank":124,"cardId":56},{"xp":17006,"rank":474,"cardId":22},{"xp":26011,"rank":446,"cardId":450},{"xp":33865,"rank":110,"cardId":23},{"xp":33171,"rank":74,"cardId":151},{"xp":21518,"rank":266,"cardId":170},{"xp":39411,"rank":98,"cardId":524},{"xp":26690,"rank":328,"cardId":521},{"xp":47528,"rank":70,"cardId":25},{"xp":44307,"rank":238,"cardId":201},{"xp":8421,"rank":308,"cardId":272},{"xp":21316,"rank":367,"cardId":236},{"xp":27880,"rank":446,"cardId":64},{"xp":29745,"rank":188,"cardId":165}]}