{"lastUpdated":1654137727237,"username":"Duhhhhhh","scores":[{"xp":6241,"rank":375,"cardId":496},{"xp":11724,"rank":432,"cardId":172},{"xp":10561,"rank":221,"cardId":493},{"xp":22285,"rank":261,"cardId":170},{"xp":6463,"rank":458,"cardId":543},{"xp":14650,"rank":238,"cardId":46},{"xp":14835,"rank":220,"cardId":47},{"xp":10702,"rank":147,"cardId":547},{"xp":22551,"rank":92,"cardId":526},{"xp":21484,"rank":160,"cardId":290},{"xp":20659,"rank":381,"cardId":48},{"xp":22026,"rank":111,"cardId":441}]}