{"lastUpdated":1652294751416,"username":"master123","scores":[{"xp":4457,"rank":385,"cardId":390},{"xp":23573,"rank":301,"cardId":45},{"xp":17915,"rank":470,"cardId":22},{"xp":43989,"rank":163,"cardId":6},{"xp":20327,"rank":452,"cardId":3},{"xp":4257,"rank":441,"cardId":308},{"xp":31394,"rank":447,"cardId":16},{"xp":21140,"rank":194,"cardId":541},{"xp":8087,"rank":485,"cardId":468},{"xp":41356,"rank":193,"cardId":13},{"xp":35641,"rank":107,"cardId":411},{"xp":32091,"rank":56,"cardId":410},{"xp":13597,"rank":295,"cardId":423},{"xp":43509,"rank":392,"cardId":44},{"xp":48116,"rank":164,"cardId":17},{"xp":58169,"rank":90,"cardId":38},{"xp":38114,"rank":463,"cardId":39}]}