{"lastUpdated":1651409974016,"username":"3than","scores":[{"xp":78668,"rank":71,"cardId":196},{"xp":8373,"rank":299,"cardId":373},{"xp":24442,"rank":428,"cardId":433},{"xp":59516,"rank":201,"cardId":115},{"xp":8791,"rank":231,"cardId":490},{"xp":20783,"rank":160,"cardId":520},{"xp":20612,"rank":289,"cardId":188},{"xp":18887,"rank":285,"cardId":311},{"xp":22043,"rank":456,"cardId":120},{"xp":77923,"rank":45,"cardId":2},{"xp":30465,"rank":155,"cardId":40},{"xp":27078,"rank":249,"cardId":45},{"xp":33360,"rank":26,"cardId":149},{"xp":26028,"rank":265,"cardId":118},{"xp":30131,"rank":375,"cardId":113},{"xp":33314,"rank":302,"cardId":217},{"xp":49938,"rank":35,"cardId":494},{"xp":29941,"rank":45,"cardId":237},{"xp":19850,"rank":387,"cardId":186},{"xp":27821,"rank":114,"cardId":500},{"xp":70372,"rank":161,"cardId":10},{"xp":7725,"rank":494,"cardId":37},{"xp":24373,"rank":354,"cardId":243},{"xp":16512,"rank":268,"cardId":415},{"xp":50848,"rank":174,"cardId":18},{"xp":79348,"rank":43,"cardId":34},{"xp":25520,"rank":275,"cardId":177},{"xp":26964,"rank":74,"cardId":528},{"xp":12827,"rank":452,"cardId":194},{"xp":82547,"rank":37,"cardId":24},{"xp":36115,"rank":272,"cardId":119},{"xp":63599,"rank":247,"cardId":108},{"xp":5851,"rank":481,"cardId":410},{"xp":20551,"rank":489,"cardId":549},{"xp":36389,"rank":31,"cardId":46},{"xp":35545,"rank":35,"cardId":47},{"xp":37077,"rank":134,"cardId":48},{"xp":28392,"rank":252,"cardId":121},{"xp":52638,"rank":254,"cardId":44},{"xp":57315,"rank":436,"cardId":265},{"xp":17855,"rank":166,"cardId":556},{"xp":20325,"rank":76,"cardId":442},{"xp":81745,"rank":339,"cardId":214},{"xp":32387,"rank":263,"cardId":564},{"xp":20939,"rank":441,"cardId":57},{"xp":113522,"rank":395,"cardId":444}]}