{"lastUpdated":1651465930821,"username":"Frisky_boi90","scores":[{"xp":17751,"rank":296,"cardId":412},{"xp":1035,"rank":475,"cardId":621},{"xp":6584,"rank":261,"cardId":680},{"xp":6084,"rank":153,"cardId":679},{"xp":5201,"rank":133,"cardId":658},{"xp":4531,"rank":226,"cardId":660},{"xp":5101,"rank":267,"cardId":659},{"xp":11299,"rank":230,"cardId":425},{"xp":6762,"rank":230,"cardId":146},{"xp":6404,"rank":119,"cardId":682},{"xp":7334,"rank":145,"cardId":683},{"xp":6969,"rank":202,"cardId":681},{"xp":6991,"rank":164,"cardId":684},{"xp":5614,"rank":124,"cardId":686},{"xp":20608,"rank":436,"cardId":168},{"xp":5974,"rank":126,"cardId":685},{"xp":15686,"rank":423,"cardId":271},{"xp":6539,"rank":171,"cardId":687}]}