{"lastUpdated":1646531229869,"username":"Geno__Sans26","scores":[{"xp":5250,"rank":347,"cardId":610},{"xp":9760,"rank":267,"cardId":565},{"xp":10972,"rank":129,"cardId":539},{"xp":36900,"rank":141,"cardId":136},{"xp":47324,"rank":74,"cardId":495},{"xp":32522,"rank":300,"cardId":217},{"xp":15058,"rank":333,"cardId":377},{"xp":29424,"rank":364,"cardId":450},{"xp":4805,"rank":391,"cardId":559},{"xp":36808,"rank":254,"cardId":11},{"xp":24788,"rank":421,"cardId":15},{"xp":19243,"rank":480,"cardId":521},{"xp":24750,"rank":272,"cardId":177},{"xp":19015,"rank":98,"cardId":557},{"xp":48938,"rank":334,"cardId":108},{"xp":18114,"rank":382,"cardId":27},{"xp":20374,"rank":112,"cardId":192},{"xp":52301,"rank":120,"cardId":17},{"xp":22691,"rank":201,"cardId":443}]}