{"lastUpdated":1654094704087,"username":"zenithal","scores":[{"xp":24474,"rank":239,"cardId":241},{"xp":18789,"rank":256,"cardId":300},{"xp":19872,"rank":325,"cardId":5},{"xp":13778,"rank":178,"cardId":562},{"xp":50204,"rank":67,"cardId":40},{"xp":6554,"rank":239,"cardId":390},{"xp":21852,"rank":316,"cardId":225},{"xp":7644,"rank":275,"cardId":467},{"xp":57158,"rank":300,"cardId":10},{"xp":20837,"rank":69,"cardId":102},{"xp":8464,"rank":401,"cardId":397},{"xp":68315,"rank":62,"cardId":13},{"xp":7679,"rank":448,"cardId":676},{"xp":7484,"rank":346,"cardId":416},{"xp":21419,"rank":426,"cardId":49},{"xp":37990,"rank":66,"cardId":426},{"xp":13469,"rank":130,"cardId":306},{"xp":42626,"rank":100,"cardId":25},{"xp":5520,"rank":350,"cardId":651},{"xp":22131,"rank":242,"cardId":235},{"xp":8465,"rank":486,"cardId":423},{"xp":71271,"rank":132,"cardId":44},{"xp":27962,"rank":83,"cardId":556},{"xp":7014,"rank":246,"cardId":630}]}