{"lastUpdated":1652391455650,"username":"bendybrox10","scores":[{"xp":20347,"rank":270,"cardId":175},{"xp":20152,"rank":222,"cardId":300},{"xp":17656,"rank":205,"cardId":51},{"xp":18677,"rank":368,"cardId":307},{"xp":2253,"rank":309,"cardId":646},{"xp":9067,"rank":186,"cardId":740},{"xp":20108,"rank":273,"cardId":143},{"xp":11584,"rank":157,"cardId":582},{"xp":10004,"rank":490,"cardId":151},{"xp":17767,"rank":110,"cardId":589},{"xp":8839,"rank":194,"cardId":606},{"xp":18641,"rank":166,"cardId":437},{"xp":19922,"rank":322,"cardId":240}]}