{"lastUpdated":1653936343347,"username":"FalonGodShiftAU","scores":[{"xp":21477,"rank":465,"cardId":638},{"xp":27637,"rank":230,"cardId":314},{"xp":14359,"rank":359,"cardId":122},{"xp":58331,"rank":42,"cardId":295},{"xp":5199,"rank":269,"cardId":303},{"xp":2782,"rank":238,"cardId":605},{"xp":9134,"rank":121,"cardId":580},{"xp":10847,"rank":489,"cardId":541},{"xp":39997,"rank":141,"cardId":243},{"xp":14884,"rank":251,"cardId":534},{"xp":27658,"rank":329,"cardId":509},{"xp":3749,"rank":239,"cardId":640},{"xp":20203,"rank":165,"cardId":418},{"xp":26633,"rank":410,"cardId":549},{"xp":29824,"rank":198,"cardId":48},{"xp":9512,"rank":458,"cardId":176},{"xp":49707,"rank":101,"cardId":616},{"xp":16400,"rank":113,"cardId":630},{"xp":38385,"rank":132,"cardId":443},{"xp":17479,"rank":90,"cardId":647},{"xp":17278,"rank":320,"cardId":697},{"xp":4122,"rank":427,"cardId":529}]}