{"lastUpdated":1648780238307,"username":"HenriIsReal","scores":[{"xp":25218,"rank":313,"cardId":136},{"xp":11061,"rank":494,"cardId":295},{"xp":3647,"rank":148,"cardId":605},{"xp":23794,"rank":206,"cardId":307},{"xp":15994,"rank":131,"cardId":12},{"xp":17338,"rank":403,"cardId":195},{"xp":3275,"rank":290,"cardId":593},{"xp":17296,"rank":352,"cardId":405},{"xp":16191,"rank":84,"cardId":228},{"xp":24273,"rank":147,"cardId":411},{"xp":28175,"rank":98,"cardId":393},{"xp":10220,"rank":344,"cardId":250},{"xp":17518,"rank":155,"cardId":523},{"xp":14825,"rank":491,"cardId":235}]}