{"lastUpdated":1649669909322,"username":"armored_yeti08","scores":[{"xp":60076,"rank":372,"cardId":401},{"xp":44814,"rank":159,"cardId":32},{"xp":6418,"rank":238,"cardId":641},{"xp":26296,"rank":143,"cardId":145},{"xp":21937,"rank":126,"cardId":662},{"xp":40430,"rank":54,"cardId":515},{"xp":26663,"rank":453,"cardId":217},{"xp":11992,"rank":107,"cardId":680},{"xp":416,"rank":429,"cardId":633},{"xp":51881,"rank":123,"cardId":450},{"xp":26647,"rank":104,"cardId":114},{"xp":6894,"rank":412,"cardId":642},{"xp":6709,"rank":240,"cardId":594},{"xp":11846,"rank":307,"cardId":532},{"xp":11077,"rank":71,"cardId":683},{"xp":31047,"rank":481,"cardId":101},{"xp":10757,"rank":88,"cardId":681},{"xp":13002,"rank":52,"cardId":684},{"xp":10168,"rank":352,"cardId":671},{"xp":13789,"rank":127,"cardId":637},{"xp":8360,"rank":458,"cardId":584},{"xp":10578,"rank":287,"cardId":674},{"xp":8445,"rank":58,"cardId":686},{"xp":33127,"rank":452,"cardId":403},{"xp":9517,"rank":457,"cardId":199},{"xp":39512,"rank":111,"cardId":271},{"xp":23745,"rank":411,"cardId":549},{"xp":44755,"rank":182,"cardId":318},{"xp":7399,"rank":461,"cardId":441},{"xp":45251,"rank":50,"cardId":566},{"xp":106717,"rank":104,"cardId":419},{"xp":10547,"rank":73,"cardId":687},{"xp":16639,"rank":270,"cardId":697},{"xp":19242,"rank":451,"cardId":564},{"xp":20420,"rank":321,"cardId":573},{"xp":1551,"rank":476,"cardId":647}]}