{"lastUpdated":1652657925187,"username":"The Mistress","scores":[{"xp":12338,"rank":268,"cardId":567},{"xp":22211,"rank":236,"cardId":312},{"xp":8687,"rank":191,"cardId":497},{"xp":37618,"rank":40,"cardId":565},{"xp":1169,"rank":232,"cardId":602},{"xp":10133,"rank":354,"cardId":220},{"xp":31811,"rank":132,"cardId":29},{"xp":4830,"rank":396,"cardId":641},{"xp":16494,"rank":74,"cardId":381},{"xp":52373,"rank":254,"cardId":105},{"xp":88232,"rank":42,"cardId":217},{"xp":9556,"rank":460,"cardId":275},{"xp":10392,"rank":101,"cardId":561},{"xp":7739,"rank":337,"cardId":493},{"xp":7869,"rank":180,"cardId":498},{"xp":53170,"rank":405,"cardId":107},{"xp":9176,"rank":329,"cardId":480},{"xp":35393,"rank":13,"cardId":659},{"xp":14948,"rank":105,"cardId":740},{"xp":18793,"rank":140,"cardId":125},{"xp":165985,"rank":14,"cardId":10},{"xp":94915,"rank":8,"cardId":592},{"xp":9551,"rank":336,"cardId":313},{"xp":18751,"rank":86,"cardId":632},{"xp":37084,"rank":142,"cardId":608},{"xp":29118,"rank":332,"cardId":20},{"xp":52280,"rank":24,"cardId":191},{"xp":36264,"rank":144,"cardId":469},{"xp":76660,"rank":164,"cardId":504},{"xp":12225,"rank":433,"cardId":527},{"xp":12045,"rank":232,"cardId":676},{"xp":11261,"rank":417,"cardId":394},{"xp":20397,"rank":50,"cardId":707},{"xp":16759,"rank":35,"cardId":507},{"xp":26448,"rank":299,"cardId":49},{"xp":134105,"rank":270,"cardId":59},{"xp":32086,"rank":67,"cardId":678},{"xp":55701,"rank":39,"cardId":664},{"xp":9116,"rank":135,"cardId":635},{"xp":9006,"rank":385,"cardId":441},{"xp":6868,"rank":217,"cardId":570},{"xp":8806,"rank":156,"cardId":727},{"xp":10498,"rank":305,"cardId":556},{"xp":29569,"rank":455,"cardId":17},{"xp":55278,"rank":188,"cardId":39},{"xp":52211,"rank":75,"cardId":315},{"xp":59404,"rank":57,"cardId":316},{"xp":118520,"rank":40,"cardId":41},{"xp":8886,"rank":179,"cardId":647},{"xp":39197,"rank":69,"cardId":726}]}