{"lastUpdated":1651829982649,"username":"Mr 72687","scores":[{"xp":258134,"rank":19,"cardId":115},{"xp":118237,"rank":97,"cardId":401},{"xp":803,"rank":225,"cardId":639},{"xp":9804,"rank":276,"cardId":166},{"xp":17604,"rank":394,"cardId":495},{"xp":18284,"rank":455,"cardId":314},{"xp":11883,"rank":44,"cardId":605},{"xp":47331,"rank":73,"cardId":404},{"xp":72202,"rank":120,"cardId":710},{"xp":225733,"rank":12,"cardId":478},{"xp":9740,"rank":130,"cardId":659},{"xp":17837,"rank":323,"cardId":148},{"xp":6475,"rank":226,"cardId":740},{"xp":226835,"rank":50,"cardId":54},{"xp":5788,"rank":368,"cardId":559},{"xp":41082,"rank":420,"cardId":163},{"xp":103488,"rank":12,"cardId":541},{"xp":20778,"rank":136,"cardId":414},{"xp":72725,"rank":77,"cardId":473},{"xp":200615,"rank":3,"cardId":477},{"xp":5782,"rank":244,"cardId":629},{"xp":14245,"rank":360,"cardId":406},{"xp":168985,"rank":28,"cardId":667},{"xp":22021,"rank":489,"cardId":20},{"xp":72485,"rank":143,"cardId":58},{"xp":3910,"rank":478,"cardId":673},{"xp":42549,"rank":59,"cardId":471},{"xp":4394,"rank":472,"cardId":583},{"xp":20861,"rank":448,"cardId":509},{"xp":20103,"rank":95,"cardId":676},{"xp":238386,"rank":5,"cardId":103},{"xp":12461,"rank":477,"cardId":194},{"xp":6127,"rank":183,"cardId":626},{"xp":5926,"rank":353,"cardId":604},{"xp":130544,"rank":19,"cardId":671},{"xp":132504,"rank":221,"cardId":52},{"xp":89424,"rank":10,"cardId":393},{"xp":116840,"rank":27,"cardId":675},{"xp":12550,"rank":387,"cardId":609},{"xp":140751,"rank":7,"cardId":674},{"xp":32303,"rank":115,"cardId":150},{"xp":116724,"rank":343,"cardId":59},{"xp":80032,"rank":36,"cardId":531},{"xp":1506,"rank":478,"cardId":685},{"xp":113367,"rank":46,"cardId":64},{"xp":44454,"rank":269,"cardId":472},{"xp":49065,"rank":301,"cardId":44},{"xp":95976,"rank":16,"cardId":474},{"xp":220007,"rank":43,"cardId":55},{"xp":47281,"rank":195,"cardId":106}]}