{"lastUpdated":1652377546845,"username":"JrJelly","scores":[{"xp":9439,"rank":64,"cardId":587},{"xp":17638,"rank":90,"cardId":563},{"xp":11541,"rank":149,"cardId":617},{"xp":37783,"rank":435,"cardId":115},{"xp":30206,"rank":113,"cardId":175},{"xp":23911,"rank":63,"cardId":562},{"xp":30949,"rank":115,"cardId":377},{"xp":19181,"rank":303,"cardId":143},{"xp":17266,"rank":89,"cardId":298},{"xp":8230,"rank":200,"cardId":547},{"xp":16614,"rank":305,"cardId":297},{"xp":6899,"rank":344,"cardId":669},{"xp":13816,"rank":224,"cardId":556}]}