{"lastUpdated":1647283208517,"username":"Azure1285","scores":[{"xp":1830,"rank":350,"cardId":619},{"xp":12354,"rank":188,"cardId":285},{"xp":16186,"rank":412,"cardId":600},{"xp":20167,"rank":137,"cardId":275},{"xp":2245,"rank":335,"cardId":679},{"xp":11054,"rank":162,"cardId":467},{"xp":22583,"rank":200,"cardId":307},{"xp":10327,"rank":90,"cardId":659},{"xp":1486,"rank":253,"cardId":628},{"xp":6555,"rank":406,"cardId":676},{"xp":2100,"rank":471,"cardId":681},{"xp":2686,"rank":351,"cardId":546},{"xp":7604,"rank":368,"cardId":306}]}