{"lastUpdated":1656023866385,"username":"Slightly_A_Weeb","scores":[{"xp":22278,"rank":72,"cardId":617},{"xp":9864,"rank":284,"cardId":610},{"xp":31324,"rank":67,"cardId":251},{"xp":25529,"rank":197,"cardId":550},{"xp":64994,"rank":181,"cardId":105},{"xp":26543,"rank":142,"cardId":56},{"xp":11621,"rank":420,"cardId":51},{"xp":23993,"rank":322,"cardId":186},{"xp":73614,"rank":225,"cardId":107},{"xp":1375,"rank":249,"cardId":633},{"xp":23271,"rank":285,"cardId":508},{"xp":45234,"rank":42,"cardId":143},{"xp":9942,"rank":16,"cardId":666},{"xp":6711,"rank":371,"cardId":291},{"xp":19657,"rank":213,"cardId":406},{"xp":1212,"rank":369,"cardId":652},{"xp":1627,"rank":430,"cardId":653},{"xp":21300,"rank":321,"cardId":608},{"xp":38657,"rank":157,"cardId":243},{"xp":42657,"rank":56,"cardId":171},{"xp":11371,"rank":349,"cardId":532},{"xp":27512,"rank":460,"cardId":202},{"xp":51478,"rank":371,"cardId":273},{"xp":17640,"rank":67,"cardId":306},{"xp":28738,"rank":390,"cardId":408},{"xp":17975,"rank":110,"cardId":669},{"xp":7897,"rank":243,"cardId":651},{"xp":22426,"rank":340,"cardId":165},{"xp":8785,"rank":365,"cardId":556}]}