{"lastUpdated":1653720399783,"username":"SupaSeby","scores":[{"xp":24256,"rank":226,"cardId":312},{"xp":40136,"rank":145,"cardId":136},{"xp":9636,"rank":465,"cardId":275},{"xp":41540,"rank":80,"cardId":111},{"xp":12646,"rank":230,"cardId":480},{"xp":30891,"rank":239,"cardId":104},{"xp":19661,"rank":227,"cardId":541},{"xp":9546,"rank":350,"cardId":313},{"xp":25292,"rank":284,"cardId":174},{"xp":28915,"rank":321,"cardId":289},{"xp":29548,"rank":43,"cardId":632},{"xp":34090,"rank":199,"cardId":243},{"xp":27612,"rank":95,"cardId":534},{"xp":30094,"rank":45,"cardId":676},{"xp":12381,"rank":377,"cardId":394},{"xp":24377,"rank":225,"cardId":299},{"xp":40314,"rank":28,"cardId":557},{"xp":14245,"rank":147,"cardId":669},{"xp":20234,"rank":165,"cardId":678},{"xp":34999,"rank":159,"cardId":165},{"xp":35888,"rank":31,"cardId":727},{"xp":11252,"rank":458,"cardId":697},{"xp":30774,"rank":117,"cardId":726}]}