[{"xp":14995,"rank":379,"cardId":175},{"xp":11592,"rank":212,"cardId":565},{"xp":11722,"rank":178,"cardId":562},{"xp":24268,"rank":243,"cardId":601},{"xp":12013,"rank":313,"cardId":607},{"xp":10965,"rank":207,"cardId":285},{"xp":19503,"rank":29,"cardId":680},{"xp":8340,"rank":408,"cardId":421},{"xp":13521,"rank":96,"cardId":438},{"xp":11140,"rank":316,"cardId":169},{"xp":13189,"rank":354,"cardId":510},{"xp":12867,"rank":492,"cardId":503},{"xp":12226,"rank":168,"cardId":298},{"xp":10155,"rank":7,"cardId":663},{"xp":14470,"rank":165,"cardId":277},{"xp":12355,"rank":91,"cardId":582},{"xp":18678,"rank":103,"cardId":624},{"xp":10673,"rank":202,"cardId":583},{"xp":15200,"rank":471,"cardId":505},{"xp":4565,"rank":430,"cardId":597}]