{"lastUpdated":1654764383881,"username":"101lvspeedrun","scores":[{"xp":9548,"rank":254,"cardId":373},{"xp":7826,"rank":281,"cardId":490},{"xp":8118,"rank":335,"cardId":610},{"xp":15233,"rank":482,"cardId":175},{"xp":11243,"rank":244,"cardId":562},{"xp":14114,"rank":477,"cardId":601},{"xp":31801,"rank":132,"cardId":160},{"xp":40586,"rank":83,"cardId":29},{"xp":22120,"rank":314,"cardId":225},{"xp":4434,"rank":304,"cardId":679},{"xp":5798,"rank":287,"cardId":498},{"xp":29342,"rank":484,"cardId":6},{"xp":4888,"rank":445,"cardId":740},{"xp":1879,"rank":386,"cardId":646},{"xp":60914,"rank":258,"cardId":10},{"xp":53091,"rank":427,"cardId":427},{"xp":2433,"rank":429,"cardId":572},{"xp":3038,"rank":309,"cardId":682},{"xp":5826,"rank":260,"cardId":588},{"xp":26916,"rank":18,"cardId":506},{"xp":11303,"rank":335,"cardId":274},{"xp":15529,"rank":495,"cardId":599},{"xp":20976,"rank":87,"cardId":583},{"xp":13604,"rank":42,"cardId":636},{"xp":3083,"rank":404,"cardId":683},{"xp":3513,"rank":474,"cardId":681},{"xp":13304,"rank":440,"cardId":194},{"xp":2871,"rank":411,"cardId":626},{"xp":13537,"rank":127,"cardId":604},{"xp":2143,"rank":393,"cardId":640},{"xp":14970,"rank":319,"cardId":584},{"xp":5438,"rank":310,"cardId":714},{"xp":52208,"rank":71,"cardId":609},{"xp":76964,"rank":108,"cardId":202},{"xp":12783,"rank":455,"cardId":297},{"xp":7295,"rank":372,"cardId":669},{"xp":6433,"rank":294,"cardId":651},{"xp":1710,"rank":486,"cardId":685},{"xp":28228,"rank":268,"cardId":236},{"xp":16388,"rank":359,"cardId":664},{"xp":7552,"rank":178,"cardId":635},{"xp":19170,"rank":270,"cardId":548},{"xp":31847,"rank":292,"cardId":616},{"xp":8758,"rank":396,"cardId":688},{"xp":5582,"rank":276,"cardId":647},{"xp":19106,"rank":275,"cardId":726}]}