{"lastUpdated":1657237103109,"username":"Levich2007","scores":[{"xp":41132,"rank":393,"cardId":1},{"xp":31454,"rank":123,"cardId":175},{"xp":26603,"rank":422,"cardId":2},{"xp":45180,"rank":79,"cardId":40},{"xp":50059,"rank":105,"cardId":136},{"xp":23613,"rank":218,"cardId":550},{"xp":53183,"rank":477,"cardId":9},{"xp":19870,"rank":333,"cardId":111},{"xp":8680,"rank":130,"cardId":679},{"xp":54333,"rank":248,"cardId":710},{"xp":6726,"rank":472,"cardId":31},{"xp":22580,"rank":255,"cardId":27},{"xp":39654,"rank":14,"cardId":659},{"xp":71590,"rank":171,"cardId":10},{"xp":16871,"rank":204,"cardId":19},{"xp":8494,"rank":442,"cardId":37},{"xp":45176,"rank":106,"cardId":140},{"xp":6629,"rank":450,"cardId":102},{"xp":63494,"rank":76,"cardId":11},{"xp":18212,"rank":36,"cardId":588},{"xp":30888,"rank":47,"cardId":632},{"xp":34223,"rank":220,"cardId":15},{"xp":46264,"rank":404,"cardId":504},{"xp":9222,"rank":461,"cardId":296},{"xp":29097,"rank":237,"cardId":177},{"xp":12270,"rank":155,"cardId":714},{"xp":51935,"rank":113,"cardId":675},{"xp":27099,"rank":140,"cardId":517},{"xp":55009,"rank":180,"cardId":549},{"xp":54133,"rank":51,"cardId":664},{"xp":271,"rank":378,"cardId":645},{"xp":23728,"rank":498,"cardId":616},{"xp":22682,"rank":66,"cardId":741},{"xp":17396,"rank":185,"cardId":176},{"xp":7774,"rank":136,"cardId":590},{"xp":56702,"rank":477,"cardId":110},{"xp":49902,"rank":78,"cardId":697},{"xp":31585,"rank":169,"cardId":726}]}