{"lastUpdated":1652737072381,"username":"AshLight","scores":[{"xp":1980,"rank":422,"cardId":587},{"xp":39100,"rank":200,"cardId":638},{"xp":23812,"rank":185,"cardId":5},{"xp":18948,"rank":403,"cardId":4},{"xp":15998,"rank":177,"cardId":220},{"xp":756,"rank":243,"cardId":639},{"xp":19591,"rank":365,"cardId":29},{"xp":12041,"rank":418,"cardId":145},{"xp":19975,"rank":481,"cardId":3},{"xp":33524,"rank":356,"cardId":11},{"xp":4998,"rank":306,"cardId":629},{"xp":37309,"rank":238,"cardId":13},{"xp":4364,"rank":142,"cardId":628},{"xp":35900,"rank":180,"cardId":15},{"xp":5193,"rank":465,"cardId":422},{"xp":9813,"rank":228,"cardId":669},{"xp":28227,"rank":147,"cardId":235}]}