[{"xp":13000,"rank":400,"cardId":300},{"xp":12938,"rank":293,"cardId":435},{"xp":16275,"rank":474,"cardId":118},{"xp":14028,"rank":347,"cardId":53},{"xp":23950,"rank":421,"cardId":710},{"xp":27455,"rank":133,"cardId":307},{"xp":3904,"rank":349,"cardId":656},{"xp":2677,"rank":369,"cardId":659},{"xp":7960,"rank":251,"cardId":514},{"xp":10600,"rank":75,"cardId":308},{"xp":7066,"rank":289,"cardId":228},{"xp":15549,"rank":404,"cardId":278},{"xp":16610,"rank":450,"cardId":177},{"xp":16108,"rank":437,"cardId":121},{"xp":2783,"rank":161,"cardId":717},{"xp":16122,"rank":222,"cardId":697},{"xp":4188,"rank":251,"cardId":647}]