{"lastUpdated":1648982324406,"username":"Tims","scores":[{"xp":3394,"rank":394,"cardId":538},{"xp":13824,"rank":443,"cardId":148},{"xp":40793,"rank":204,"cardId":20},{"xp":33274,"rank":217,"cardId":15},{"xp":38487,"rank":294,"cardId":141},{"xp":6908,"rank":370,"cardId":589},{"xp":26082,"rank":326,"cardId":168},{"xp":12896,"rank":298,"cardId":523},{"xp":36048,"rank":92,"cardId":235},{"xp":11798,"rank":314,"cardId":47},{"xp":23157,"rank":82,"cardId":571},{"xp":26623,"rank":128,"cardId":566},{"xp":42592,"rank":370,"cardId":44}]}