{"lastUpdated":1654760160987,"username":"Event Horizon","scores":[{"xp":5838,"rank":430,"cardId":610},{"xp":8441,"rank":107,"cardId":618},{"xp":7084,"rank":468,"cardId":562},{"xp":9271,"rank":323,"cardId":191},{"xp":38553,"rank":240,"cardId":20},{"xp":21711,"rank":266,"cardId":299},{"xp":8696,"rank":151,"cardId":650},{"xp":4671,"rank":487,"cardId":604},{"xp":9086,"rank":279,"cardId":649},{"xp":8476,"rank":313,"cardId":669},{"xp":7321,"rank":379,"cardId":545},{"xp":30987,"rank":124,"cardId":235},{"xp":15638,"rank":383,"cardId":197},{"xp":17781,"rank":410,"cardId":266}]}