{"lastUpdated":1653368348333,"username":"Event Horizon","scores":[{"xp":5838,"rank":417,"cardId":610},{"xp":8441,"rank":97,"cardId":618},{"xp":7084,"rank":460,"cardId":562},{"xp":9271,"rank":315,"cardId":191},{"xp":38553,"rank":238,"cardId":20},{"xp":21711,"rank":255,"cardId":299},{"xp":8696,"rank":143,"cardId":650},{"xp":4671,"rank":478,"cardId":604},{"xp":9086,"rank":256,"cardId":649},{"xp":8476,"rank":291,"cardId":669},{"xp":7321,"rank":373,"cardId":545},{"xp":30987,"rank":122,"cardId":235},{"xp":15638,"rank":377,"cardId":197},{"xp":17781,"rank":400,"cardId":266}]}