{"lastUpdated":1651078898914,"username":"gasterunder","scores":[{"xp":7916,"rank":417,"cardId":479},{"xp":13463,"rank":299,"cardId":275},{"xp":8604,"rank":238,"cardId":467},{"xp":10426,"rank":243,"cardId":436},{"xp":15055,"rank":457,"cardId":142},{"xp":15428,"rank":132,"cardId":480},{"xp":27705,"rank":223,"cardId":434},{"xp":7402,"rank":311,"cardId":514},{"xp":8100,"rank":497,"cardId":125},{"xp":13308,"rank":183,"cardId":313},{"xp":8143,"rank":334,"cardId":298},{"xp":2994,"rank":181,"cardId":652},{"xp":18243,"rank":189,"cardId":394},{"xp":5168,"rank":293,"cardId":649},{"xp":19274,"rank":476,"cardId":49},{"xp":12781,"rank":321,"cardId":523},{"xp":11682,"rank":329,"cardId":290},{"xp":17138,"rank":52,"cardId":727},{"xp":46437,"rank":191,"cardId":41},{"xp":26522,"rank":111,"cardId":726}]}