{"lastUpdated":1652236238087,"username":"kanny","scores":[{"xp":5551,"rank":486,"cardId":285},{"xp":4587,"rank":39,"cardId":729},{"xp":4342,"rank":156,"cardId":621},{"xp":7817,"rank":221,"cardId":193},{"xp":10981,"rank":147,"cardId":740},{"xp":12954,"rank":40,"cardId":682},{"xp":14901,"rank":297,"cardId":215},{"xp":10563,"rank":180,"cardId":161},{"xp":15110,"rank":141,"cardId":583},{"xp":11149,"rank":412,"cardId":415},{"xp":6647,"rank":69,"cardId":657},{"xp":14985,"rank":107,"cardId":714},{"xp":17830,"rank":48,"cardId":635},{"xp":16370,"rank":350,"cardId":197},{"xp":14310,"rank":486,"cardId":573},{"xp":16957,"rank":135,"cardId":581}]}