{"lastUpdated":1656758330623,"username":"LengthyNuggets","scores":[{"xp":3811,"rank":197,"cardId":619},{"xp":7869,"rank":482,"cardId":499},{"xp":5893,"rank":376,"cardId":611},{"xp":12883,"rank":238,"cardId":317},{"xp":3687,"rank":489,"cardId":303},{"xp":12173,"rank":91,"cardId":519},{"xp":10540,"rank":299,"cardId":740},{"xp":16137,"rank":454,"cardId":143},{"xp":3368,"rank":312,"cardId":572},{"xp":7310,"rank":70,"cardId":743},{"xp":27438,"rank":393,"cardId":424},{"xp":8449,"rank":308,"cardId":581}]}