{"lastUpdated":1655321666335,"username":"FemboyCharaSock","scores":[{"xp":14498,"rank":119,"cardId":400},{"xp":11230,"rank":284,"cardId":565},{"xp":18381,"rank":441,"cardId":434},{"xp":11853,"rank":437,"cardId":145},{"xp":8741,"rank":378,"cardId":385},{"xp":16266,"rank":277,"cardId":275},{"xp":17181,"rank":170,"cardId":480},{"xp":10595,"rank":346,"cardId":479},{"xp":14451,"rank":209,"cardId":313},{"xp":20161,"rank":63,"cardId":629},{"xp":10455,"rank":277,"cardId":397},{"xp":23330,"rank":68,"cardId":727}]}